{
  "pid": "6",
  "question": "As shown in the figure, if CB = 4.0, DB = 7.0, and D is the midpoint of AC, then the length of AC is ()",
  "qtype": "multi_choice",
  "answer_type": "text",
  "category": "math-targeted-vqa",
  "ground_truth": "6cm",
  "greedy_pred": "6cm",
  "greedy_finished": true,
  "greedy_correct": true,
  "n_samples": 20,
  "n_truncated": 0,
  "n_valid_samples": 20,
  "sample_preds": [
    "6cm",
    "6cm",
    "6cm",
    "6cm",
    "6cm",
    "6cm",
    "6cm",
    "6cm",
    "6cm",
    "6cm",
    "6cm",
    "6cm",
    "6cm",
    "6cm",
    "6cm",
    "6cm",
    "6cm",
    "6cm",
    "6cm",
    "6cm"
  ],
  "n_sample_correct": 20,
  "answer_counts": {
    "num:6.0": 20
  },
  "n_distinct_answers": 1,
  "top_answer": "6cm",
  "top_share": 1.0,
  "oracle_hit": true,
  "vote_winner": "6cm",
  "vote_correct": true
}