{
  "pid": "13",
  "question": "How many objects are preferred by more than 90 percent of people in at least one category?",
  "qtype": "free_form",
  "answer_type": "integer",
  "category": "general-vqa",
  "ground_truth": "0",
  "greedy_pred": "0.0",
  "greedy_finished": true,
  "greedy_correct": true,
  "n_samples": 20,
  "n_truncated": 2,
  "n_valid_samples": 18,
  "sample_preds": [
    "0.0",
    "0.0",
    "0.0",
    "0.0",
    "0.0",
    "0.0",
    "0.0",
    "0.0",
    "0.0",
    "0.0",
    "0.0",
    "0.0",
    "0.0",
    "0.0",
    "0.0",
    "0.0",
    "0.0",
    "0.0"
  ],
  "n_sample_correct": 18,
  "answer_counts": {
    "num:0.0": 18
  },
  "n_distinct_answers": 1,
  "top_answer": "0.0",
  "top_share": 1.0,
  "oracle_hit": true,
  "vote_winner": "0.0",
  "vote_correct": true
}